pythondev_example/__init__.py
pythondev_example/console.py
pythondev_example/wikipedia.py
pythondev_example-0.1.0.dist-info/entry_points.txt
pythondev_example-0.1.0.dist-info/LICENSE
pythondev_example-0.1.0.dist-info/WHEEL
pythondev_example-0.1.0.dist-info/METADATA
pythondev_example-0.1.0.dist-info/RECORD
